shapmat/PCA.py
shapmat/PCA_plot.py
shapmat/__init__.py
shapmat/abundance_filter.py
shapmat/clustering.py
shapmat/clustering_plot.py
shapmat/explainer.py
shapmat/shap_plot.py
shapmat-0.1.5.dist-info/LICENCE.txt
shapmat-0.1.5.dist-info/METADATA
shapmat-0.1.5.dist-info/WHEEL
shapmat-0.1.5.dist-info/top_level.txt
shapmat-0.1.5.dist-info/RECORD
